LICENSE
README.md
pyproject.toml
setup.py
soccer_api_wrapper/__init__.py
soccer_api_wrapper/soccerapi.py
soccer_api_wrapper.egg-info/PKG-INFO
soccer_api_wrapper.egg-info/SOURCES.txt
soccer_api_wrapper.egg-info/dependency_links.txt
soccer_api_wrapper.egg-info/requires.txt
soccer_api_wrapper.egg-info/top_level.txt
soccer_api_wrapper/tests/soccerapi_test.py