Metadata-Version: 2.1
Name: soccer-api-wrapper
Version: 0.1.1
Summary: Soccer Api Wrapper
Author-email: Debi Ejeta <dme2136@columbia.edu>
License:                                  Apache License
Project-URL: repository, https://github.com/Debi-Ejeta/soccer-api-wrapper
Classifier: Development Status :: 2 - Pre-Alpha
Classifier: Programming Language :: Python :: Implementation :: CPython
Classifier: Programming Language :: Python :: Implementation :: PyPy
Classifier: Programming Language :: Python :: 3
Classifier: Programming Language :: Python :: 3.7
Classifier: Programming Language :: Python :: 3.8
Classifier: Programming Language :: Python :: 3.9
Classifier: Programming Language :: Python :: 3.10
Classifier: Programming Language :: Python :: 3.11
Requires-Python: >=3.7
Provides-Extra: develop
License-File: LICENSE
